optilabfe/FrontendClientRunner.py
optilabfe/OptConstraint.py
optilabfe/OptMPModel.py
optilabfe/OptObject.py
optilabfe/OptVariable.py
optilabfe/OptimizerMPModel.py
optilabfe/OptimizerRoutingModel.py
optilabfe/Parallel.py
optilabfe/ParallelMPToolbox.py
optilabfe/ParallelModel.py
optilabfe/ParallelRoutingToolbox.py
optilabfe/VRPRoutingModel.py
optilabfe/cp_routing_model_pb2.py
optilabfe/linear_model_pb2.py
optilabfe/meta_bb_packet_pb2.py
optilabfe/meta_bb_paramset_pb2.py
optilabfe/network_packet_pb2.py
optilabfe/optilab_pb2.py
optilabfe/optimizer_model_pb2.py
optilabfe/parallelbb_parameter_set_pb2.py
optilabfe/routing_model_pb2.py
OptiLabFE-0.4.dist-info/LICENSE
OptiLabFE-0.4.dist-info/METADATA
OptiLabFE-0.4.dist-info/WHEEL
OptiLabFE-0.4.dist-info/top_level.txt
OptiLabFE-0.4.dist-info/RECORD
