Metadata-Version: 2.1
Name: OptiLabFE
Version: 0.4
Summary: Front-end for Parallel-OptiLab package
Home-page: https://www.parallel-ai.com
Author: Parallel team
Author-email: fede.campe@gmail.com
License: UNKNOWN
Platform: UNKNOWN
Classifier: Programming Language :: Python :: 3
Classifier: License :: OSI Approved :: MIT License
Classifier: Operating System :: OS Independent
